dbxdebug/__init__.py
dbxdebug/capture_io.py
dbxdebug/cli.py
dbxdebug/dbx_kbd.py
dbxdebug/gdb.py
dbxdebug/html.py
dbxdebug/keyboard.py
dbxdebug/qmp.py
dbxdebug/utils.py
dbxdebug/video.py
dbxdebug-0.2.1.dist-info/METADATA
dbxdebug-0.2.1.dist-info/WHEEL
dbxdebug-0.2.1.dist-info/entry_points.txt
dbxdebug-0.2.1.dist-info/RECORD
