Metadata-Version: 2.4
Name: dbxdebug
Version: 0.2.1
Summary: Client library and CLI for DOSBox-X remote debug protocols (GDB and QMP)
Author: lokkju
License-Expression: MIT
Keywords: debugging,dosbox,dosbox-x,emulator,gdb,qmp
Classifier: Development Status :: 3 - Alpha
Classifier: Environment :: Console
Classifier: Intended Audience :: Developers
Classifier: License :: OSI Approved :: MIT License
Classifier: Operating System :: POSIX
Classifier: Programming Language :: Python :: 3.11
Classifier: Programming Language :: Python :: 3.12
Classifier: Topic :: Software Development :: Debuggers
Classifier: Topic :: System :: Emulators
Requires-Python: >=3.11
Requires-Dist: click>=8.0
Requires-Dist: loguru>=0.7
